{"nodes": [{"id": "static_logo_png", "label": "Prumo ERP Logo", "file_type": "image", "source_file": "static/logo.png", "source_location": null}, {"id": "prumo_erp_concept", "label": "Prumo ERP - Software de Constru\u00e7\u00e3o Civil", "file_type": "concept", "source_file": "static/logo.png", "source_location": null}, {"id": "static_logo_png", "label": "Prumo ERP Logo", "file_type": "image", "source_file": "static/logo.png"}, {"id": "prumo_erp_concept", "label": "Prumo ERP - Software de Constru\u00e7\u00e3o Civil", "file_type": "concept", "source_file": "static/logo.png"}], "edges": [{"source": "static_logo_png", "target": "prumo_erp_concept", "relation": "references", "confidence": "EXTRACTED", "confidence_score": 1.0, "source_file": "static/logo.png"}, {"source": "static_logo_png", "target": "prumo_erp_concept", "relation": "references", "confidence": "EXTRACTED", "confidence_score": 1.0, "source_file": "static/logo.png"}], "hyperedges": []}